<annotation>
	<folder>train</folder>
	<filename>대한안과학회118회학술대회.png</filename>
	<path>C:\Users\user\Documents\lab\data\images\train\대한안과학회118회학술대회.png</path>
	<source>
		<database>Unknown</database>
	</source>
	<size>
		<width>1103</width>
		<height>771</height>
		<depth>3</depth>
	</size>
	<segmented>0</segmented>
	<object>
		<name>boundary</name>
		<pose>Unspecified</pose>
		<truncated>0</truncated>
		<difficult>0</difficult>
		<bndbox>
			<xmin>343</xmin>
			<ymin>115</ymin>
			<xmax>591</xmax>
			<ymax>613</ymax>
		</bndbox>
	</object>
	<object>
		<name>boundary</name>
		<pose>Unspecified</pose>
		<truncated>0</truncated>
		<difficult>0</difficult>
		<bndbox>
			<xmin>640</xmin>
			<ymin>377</ymin>
			<xmax>839</xmax>
			<ymax>577</ymax>
		</bndbox>
	</object>
	<object>
		<name>booth</name>
		<pose>Unspecified</pose>
		<truncated>0</truncated>
		<difficult>0</difficult>
		<bndbox>
			<xmin>398</xmin>
			<ymin>117</ymin>
			<xmax>455</xmax>
			<ymax>236</ymax>
		</bndbox>
	</object>
	<object>
		<name>booth</name>
		<pose>Unspecified</pose>
		<truncated>0</truncated>
		<difficult>0</difficult>
		<bndbox>
			<xmin>527</xmin>
			<ymin>117</ymin>
			<xmax>584</xmax>
			<ymax>236</ymax>
		</bndbox>
	</object>
	<object>
		<name>booth</name>
		<pose>Unspecified</pose>
		<truncated>0</truncated>
		<difficult>0</difficult>
		<bndbox>
			<xmin>501</xmin>
			<ymin>264</ymin>
			<xmax>558</xmax>
			<ymax>383</ymax>
		</bndbox>
	</object>
	<object>
		<name>booth</name>
		<pose>Unspecified</pose>
		<truncated>0</truncated>
		<difficult>0</difficult>
		<bndbox>
			<xmin>423</xmin>
			<ymin>265</ymin>
			<xmax>480</xmax>
			<ymax>384</ymax>
		</bndbox>
	</object>
	<object>
		<name>booth</name>
		<pose>Unspecified</pose>
		<truncated>0</truncated>
		<difficult>0</difficult>
		<bndbox>
			<xmin>342</xmin>
			<ymin>266</ymin>
			<xmax>403</xmax>
			<ymax>324</ymax>
		</bndbox>
	</object>
	<object>
		<name>booth</name>
		<pose>Unspecified</pose>
		<truncated>0</truncated>
		<difficult>0</difficult>
		<bndbox>
			<xmin>338</xmin>
			<ymin>325</ymin>
			<xmax>399</xmax>
			<ymax>383</ymax>
		</bndbox>
	</object>
	<object>
		<name>booth</name>
		<pose>Unspecified</pose>
		<truncated>0</truncated>
		<difficult>0</difficult>
		<bndbox>
			<xmin>364</xmin>
			<ymin>403</ymin>
			<xmax>448</xmax>
			<ymax>460</ymax>
		</bndbox>
	</object>
	<object>
		<name>booth</name>
		<pose>Unspecified</pose>
		<truncated>0</truncated>
		<difficult>0</difficult>
		<bndbox>
			<xmin>474</xmin>
			<ymin>405</ymin>
			<xmax>558</xmax>
			<ymax>462</ymax>
		</bndbox>
	</object>
	<object>
		<name>booth</name>
		<pose>Unspecified</pose>
		<truncated>0</truncated>
		<difficult>0</difficult>
		<bndbox>
			<xmin>480</xmin>
			<ymin>494</ymin>
			<xmax>564</xmax>
			<ymax>551</ymax>
		</bndbox>
	</object>
	<object>
		<name>booth</name>
		<pose>Unspecified</pose>
		<truncated>0</truncated>
		<difficult>0</difficult>
		<bndbox>
			<xmin>393</xmin>
			<ymin>494</ymin>
			<xmax>477</xmax>
			<ymax>551</ymax>
		</bndbox>
	</object>
	<object>
		<name>booth</name>
		<pose>Unspecified</pose>
		<truncated>0</truncated>
		<difficult>0</difficult>
		<bndbox>
			<xmin>395</xmin>
			<ymin>582</ymin>
			<xmax>482</xmax>
			<ymax>611</ymax>
		</bndbox>
	</object>
	<object>
		<name>booth</name>
		<pose>Unspecified</pose>
		<truncated>0</truncated>
		<difficult>0</difficult>
		<bndbox>
			<xmin>528</xmin>
			<ymin>582</ymin>
			<xmax>588</xmax>
			<ymax>611</ymax>
		</bndbox>
	</object>
	<object>
		<name>booth</name>
		<pose>Unspecified</pose>
		<truncated>0</truncated>
		<difficult>0</difficult>
		<bndbox>
			<xmin>344</xmin>
			<ymin>494</ymin>
			<xmax>371</xmax>
			<ymax>551</ymax>
		</bndbox>
	</object>
	<object>
		<name>booth</name>
		<pose>Unspecified</pose>
		<truncated>0</truncated>
		<difficult>0</difficult>
		<bndbox>
			<xmin>498</xmin>
			<ymin>581</ymin>
			<xmax>527</xmax>
			<ymax>612</ymax>
		</bndbox>
	</object>
	<object>
		<name>booth</name>
		<pose>Unspecified</pose>
		<truncated>0</truncated>
		<difficult>0</difficult>
		<bndbox>
			<xmin>637</xmin>
			<ymin>467</ymin>
			<xmax>669</xmax>
			<ymax>483</ymax>
		</bndbox>
	</object>
	<object>
		<name>booth</name>
		<pose>Unspecified</pose>
		<truncated>0</truncated>
		<difficult>0</difficult>
		<bndbox>
			<xmin>639</xmin>
			<ymin>488</ymin>
			<xmax>671</xmax>
			<ymax>504</ymax>
		</bndbox>
	</object>
	<object>
		<name>booth</name>
		<pose>Unspecified</pose>
		<truncated>0</truncated>
		<difficult>0</difficult>
		<bndbox>
			<xmin>644</xmin>
			<ymin>505</ymin>
			<xmax>676</xmax>
			<ymax>521</ymax>
		</bndbox>
	</object>
	<object>
		<name>booth</name>
		<pose>Unspecified</pose>
		<truncated>0</truncated>
		<difficult>0</difficult>
		<bndbox>
			<xmin>647</xmin>
			<ymin>519</ymin>
			<xmax>681</xmax>
			<ymax>538</ymax>
		</bndbox>
	</object>
	<object>
		<name>booth</name>
		<pose>Unspecified</pose>
		<truncated>0</truncated>
		<difficult>0</difficult>
		<bndbox>
			<xmin>657</xmin>
			<ymin>533</ymin>
			<xmax>693</xmax>
			<ymax>550</ymax>
		</bndbox>
	</object>
	<object>
		<name>booth</name>
		<pose>Unspecified</pose>
		<truncated>0</truncated>
		<difficult>0</difficult>
		<bndbox>
			<xmin>690</xmin>
			<ymin>534</ymin>
			<xmax>702</xmax>
			<ymax>572</ymax>
		</bndbox>
	</object>
	<object>
		<name>booth</name>
		<pose>Unspecified</pose>
		<truncated>0</truncated>
		<difficult>0</difficult>
		<bndbox>
			<xmin>707</xmin>
			<ymin>544</ymin>
			<xmax>722</xmax>
			<ymax>573</ymax>
		</bndbox>
	</object>
	<object>
		<name>booth</name>
		<pose>Unspecified</pose>
		<truncated>0</truncated>
		<difficult>0</difficult>
		<bndbox>
			<xmin>727</xmin>
			<ymin>380</ymin>
			<xmax>742</xmax>
			<ymax>409</ymax>
		</bndbox>
	</object>
	<object>
		<name>booth</name>
		<pose>Unspecified</pose>
		<truncated>0</truncated>
		<difficult>0</difficult>
		<bndbox>
			<xmin>743</xmin>
			<ymin>381</ymin>
			<xmax>758</xmax>
			<ymax>410</ymax>
		</bndbox>
	</object>
	<object>
		<name>booth</name>
		<pose>Unspecified</pose>
		<truncated>0</truncated>
		<difficult>0</difficult>
		<bndbox>
			<xmin>761</xmin>
			<ymin>387</ymin>
			<xmax>776</xmax>
			<ymax>416</ymax>
		</bndbox>
	</object>
	<object>
		<name>booth</name>
		<pose>Unspecified</pose>
		<truncated>0</truncated>
		<difficult>0</difficult>
		<bndbox>
			<xmin>778</xmin>
			<ymin>395</ymin>
			<xmax>793</xmax>
			<ymax>424</ymax>
		</bndbox>
	</object>
	<object>
		<name>booth</name>
		<pose>Unspecified</pose>
		<truncated>0</truncated>
		<difficult>0</difficult>
		<bndbox>
			<xmin>799</xmin>
			<ymin>446</ymin>
			<xmax>833</xmax>
			<ymax>463</ymax>
		</bndbox>
	</object>
	<object>
		<name>booth</name>
		<pose>Unspecified</pose>
		<truncated>0</truncated>
		<difficult>0</difficult>
		<bndbox>
			<xmin>793</xmin>
			<ymin>432</ymin>
			<xmax>827</xmax>
			<ymax>449</ymax>
		</bndbox>
	</object>
	<object>
		<name>booth</name>
		<pose>Unspecified</pose>
		<truncated>0</truncated>
		<difficult>0</difficult>
		<bndbox>
			<xmin>789</xmin>
			<ymin>414</ymin>
			<xmax>823</xmax>
			<ymax>431</ymax>
		</bndbox>
	</object>
	<object>
		<name>exit</name>
		<pose>Unspecified</pose>
		<truncated>0</truncated>
		<difficult>0</difficult>
		<bndbox>
			<xmin>587</xmin>
			<ymin>296</ymin>
			<xmax>599</xmax>
			<ymax>317</ymax>
		</bndbox>
	</object>
	<object>
		<name>exit</name>
		<pose>Unspecified</pose>
		<truncated>0</truncated>
		<difficult>0</difficult>
		<bndbox>
			<xmin>586</xmin>
			<ymin>325</ymin>
			<xmax>599</xmax>
			<ymax>341</ymax>
		</bndbox>
	</object>
	<object>
		<name>exit</name>
		<pose>Unspecified</pose>
		<truncated>0</truncated>
		<difficult>0</difficult>
		<bndbox>
			<xmin>642</xmin>
			<ymin>378</ymin>
			<xmax>661</xmax>
			<ymax>401</ymax>
		</bndbox>
	</object>
	<object>
		<name>exit</name>
		<pose>Unspecified</pose>
		<truncated>0</truncated>
		<difficult>0</difficult>
		<bndbox>
			<xmin>772</xmin>
			<ymin>495</ymin>
			<xmax>815</xmax>
			<ymax>539</ymax>
		</bndbox>
	</object>
	<object>
		<name>exit</name>
		<pose>Unspecified</pose>
		<truncated>0</truncated>
		<difficult>0</difficult>
		<bndbox>
			<xmin>586</xmin>
			<ymin>545</ymin>
			<xmax>599</xmax>
			<ymax>575</ymax>
		</bndbox>
	</object>
	<object>
		<name>exit</name>
		<pose>Unspecified</pose>
		<truncated>0</truncated>
		<difficult>0</difficult>
		<bndbox>
			<xmin>336</xmin>
			<ymin>585</ymin>
			<xmax>353</xmax>
			<ymax>615</ymax>
		</bndbox>
	</object>
	<object>
		<name>entrance</name>
		<pose>Unspecified</pose>
		<truncated>0</truncated>
		<difficult>0</difficult>
		<bndbox>
			<xmin>337</xmin>
			<ymin>585</ymin>
			<xmax>351</xmax>
			<ymax>617</ymax>
		</bndbox>
	</object>
	<object>
		<name>entrance</name>
		<pose>Unspecified</pose>
		<truncated>0</truncated>
		<difficult>0</difficult>
		<bndbox>
			<xmin>587</xmin>
			<ymin>545</ymin>
			<xmax>598</xmax>
			<ymax>577</ymax>
		</bndbox>
	</object>
	<object>
		<name>entrance</name>
		<pose>Unspecified</pose>
		<truncated>0</truncated>
		<difficult>0</difficult>
		<bndbox>
			<xmin>586</xmin>
			<ymin>323</ymin>
			<xmax>599</xmax>
			<ymax>341</ymax>
		</bndbox>
	</object>
	<object>
		<name>entrance</name>
		<pose>Unspecified</pose>
		<truncated>0</truncated>
		<difficult>0</difficult>
		<bndbox>
			<xmin>588</xmin>
			<ymin>297</ymin>
			<xmax>601</xmax>
			<ymax>314</ymax>
		</bndbox>
	</object>
	<object>
		<name>entrance</name>
		<pose>Unspecified</pose>
		<truncated>0</truncated>
		<difficult>0</difficult>
		<bndbox>
			<xmin>640</xmin>
			<ymin>377</ymin>
			<xmax>663</xmax>
			<ymax>405</ymax>
		</bndbox>
	</object>
	<object>
		<name>entrance</name>
		<pose>Unspecified</pose>
		<truncated>0</truncated>
		<difficult>0</difficult>
		<bndbox>
			<xmin>771</xmin>
			<ymin>497</ymin>
			<xmax>817</xmax>
			<ymax>541</ymax>
		</bndbox>
	</object>
</annotation>
